alber_package_calc/calc.py
alber_package_calc/consts.py
alber_package_calc-0.0.1.dist-info/METADATA
alber_package_calc-0.0.1.dist-info/WHEEL
alber_package_calc-0.0.1.dist-info/entry_points.txt
alber_package_calc-0.0.1.dist-info/license_files/LICENSE
alber_package_calc-0.0.1.dist-info/RECORD
