Metadata-Version: 2.1
Name: alber-package-calc
Version: 0.0.1
Summary: Ejemplo de como crear un paquete
Project-URL: Bug Tracker, https://github.com/albertorc87/subir-paquete-pypi/issues
Project-URL: Homepage, https://github.com/albertorc87/subir-paquete-pypi
Author-email: alberrc87 <alberto.r.caballero.87@gmail.com>
License: MIT License
Classifier: License :: OSI Approved :: MIT License
Classifier: Operating System :: OS Independent
Classifier: Programming Language :: Python :: 3
Requires-Python: >=3.9
